example/__init__.py
example/asset_example.py
loguru_dagster/__init__.py
loguru_dagster/bridge.py
loguru_dagster/cli.py
loguru_dagster-0.1.6.dist-info/licenses/LICENSE
test/test_bridge.py
loguru_dagster-0.1.6.dist-info/METADATA
loguru_dagster-0.1.6.dist-info/WHEEL
loguru_dagster-0.1.6.dist-info/entry_points.txt
loguru_dagster-0.1.6.dist-info/top_level.txt
loguru_dagster-0.1.6.dist-info/RECORD
