Metadata-Version: 2.4
Name: loguru-dagster
Version: 0.1.6
Summary: A bridge to integrate Loguru logging with Dagster context.log.
Author-email: Ahmet Sahiner <ahmethasimsahiner@gmail.com>
License-Expression: MIT
Project-URL: Homepage, https://github.com/albertfast/loguru-dagster
Project-URL: Repository, https://github.com/albertfast/loguru-dagster
Requires-Python: >=3.8
License-File: LICENSE
Requires-Dist: loguru>=0.7.2
Requires-Dist: dagster>=1.5.0
Requires-Dist: dagster-webserver>=1.5.0
Requires-Dist: dagster-dg-cli>=1.5.0
Provides-Extra: dev
Requires-Dist: pytest>=8.0; extra == "dev"
Requires-Dist: ipython; extra == "dev"
Requires-Dist: black; extra == "dev"
Requires-Dist: ruff; extra == "dev"
Requires-Dist: build; extra == "dev"
Requires-Dist: twine; extra == "dev"
Dynamic: license-file
